LICENSE.rst
cms_helpers/__init__.py
cms_helpers/anylink_extensions.py
cms_helpers/cms_toolbars.py
cms_helpers/filer_fields.py
cms_helpers/templatetags/__init__.py
cms_helpers/templatetags/cms_helpers.py
django_cms_helpers-2.0.0.dist-info/LICENSE.rst
django_cms_helpers-2.0.0.dist-info/METADATA
django_cms_helpers-2.0.0.dist-info/WHEEL
django_cms_helpers-2.0.0.dist-info/RECORD
