Metadata-Version: 2.1
Name: django-cms-helpers
Version: 2.0.0
Summary: django-cms-helpers is a collection of helpers when working with django-cms.
Home-page: https://github.com/stephrdev/django-cms-helpers
License: MIT
Author: Stephan Jaekel
Author-email: steph@rdev.info
Requires-Python: >=3.8,<4
Classifier: Development Status :: 5 - Production/Stable
Classifier: Environment :: Web Environment
Classifier: Framework :: Django
Classifier: Intended Audience :: Developers
Classifier: License :: OSI Approved :: MIT License
Classifier: Operating System :: Unix
Classifier: Programming Language :: Python
Classifier: Programming Language :: Python :: 3
Classifier: Programming Language :: Python :: 3.8
Classifier: Programming Language :: Python :: 3.9
Classifier: Programming Language :: Python :: 3.10
Classifier: Programming Language :: Python :: 3.11
Classifier: Programming Language :: Python :: 3
Provides-Extra: docs
Requires-Dist: Django (>=3.2)
Requires-Dist: Sphinx (>=5.1) ; extra == "docs"
Requires-Dist: django-anylink (>=2.0) ; extra == "docs"
Requires-Dist: django-cms (>=3.9)
Requires-Dist: django-filer (>=2.2) ; extra == "docs"
Project-URL: Repository, https://github.com/stephrdev/django-cms-helpers
